{
"type": "FeatureCollection",
"crs": { "type": "name", "properties": { "name": "urn:ogc:def:crs:OGC:1.3:CRS84" } },
"features": [
{ "type": "Feature", "properties": { "LOCATION": null, "COUNTY": "VANDERBURGH", "STFIPS": null, "STATE": null, "LONG": 0.0, "LAT": 0.0, "TYPE": "ASOS LAWRS COOP AB AIR SAMPLING STATION ASOS-NWS", "BWQID": 0.0, "BCU": null, "coord": 0.0, "coord2": 0.0, "ID": null, "AGENCY": null, "AGENCY_COD": 0.0, "STATION": null, "ST_DEPTH": 0.0, "CU": null, "SEG": null, "MILE": 0.0, "ONOFF": null, "BSTAT_ID": null, "COOP": 122738.0, "CLIMATE": 7.0, "WBAN": 93817.0, "NWS": "NWS", "NWS_ID": "EVV", "STN_NAME": "EVANSVILLE REGIONAL AP", "ELEV": 400.0, "LAT_DD": 38.044167, "LONG_DD": -87.520556 }, "geometry": { "type": "Point", "coordinates": [ -87.520556, 38.044167 ] } },
{ "type": "Feature", "properties": { "LOCATION": null, "COUNTY": "POSEY", "STFIPS": null, "STATE": null, "LONG": 0.0, "LAT": 0.0, "TYPE": "COOP AB COOP-A", "BWQID": 0.0, "BCU": null, "coord": 0.0, "coord2": 0.0, "ID": null, "AGENCY": null, "AGENCY_COD": 0.0, "STATION": null, "ST_DEPTH": 0.0, "CU": null, "SEG": null, "MILE": 0.0, "ONOFF": null, "BSTAT_ID": null, "COOP": 126001.0, "CLIMATE": 7.0, "WBAN": 0.0, "NWS": null, "NWS_ID": "MTVI3", "STN_NAME": "MT VERNON", "ELEV": 357.0, "LAT_DD": 37.928611, "LONG_DD": -87.895556 }, "geometry": { "type": "Point", "coordinates": [ -87.895556, 37.928611 ] } }
]
}
